Metadata-Version: 2.1
Name: nigeria
Version: 0.0.1
Summary: An API for nigeria
Home-page: UNKNOWN
Author: Odeyemi Increase Ayobami
Author-email: odeyemiincrease@yahoo.com
License: MIT
Keywords: Africa,Nigeria
Platform: UNKNOWN
Classifier: Development Status :: 5 - Production/Stable
Classifier: Intended Audience :: Education
Classifier: Operating System :: Microsoft :: Windows :: Windows 10
Classifier: License :: OSI Approved :: MIT License
Classifier: Programming Language :: Python :: 3
License-File: LICENSE.txt
